mplscience/__init__.py
mplscience/_styledata/__init__.py
mplscience/_styledata/default.py
mplscience/_styledata/despine.py
mplscience/core.py
mplscience-0.0.7.dist-info/LICENSE
mplscience-0.0.7.dist-info/WHEEL
mplscience-0.0.7.dist-info/METADATA
mplscience-0.0.7.dist-info/RECORD
