Metadata-Version: 2.1
Name: mplscience
Version: 0.0.7
Summary: Matplotlib style for scientific publications.
Home-page: https://github.com/adamgayoso/mplscience
License: MIT
Author: Adam Gayoso
Author-email: adamgayoso@berkeley.edu
Requires-Python: >=3.6.1,<4.0
Classifier: Development Status :: 4 - Beta
Classifier: Intended Audience :: Science/Research
Classifier: License :: OSI Approved :: MIT License
Classifier: Natural Language :: English
Classifier: Operating System :: MacOS :: MacOS X
Classifier: Operating System :: Microsoft :: Windows
Classifier: Operating System :: POSIX :: Linux
Classifier: Programming Language :: Python :: 3
Classifier: Programming Language :: Python :: 3.7
Classifier: Programming Language :: Python :: 3.8
Classifier: Programming Language :: Python :: 3.9
Classifier: Programming Language :: Python :: 3.10
Classifier: Programming Language :: Python :: 3.11
Classifier: Programming Language :: Python :: 3.6
Classifier: Programming Language :: Python :: 3.7
Classifier: Programming Language :: Python :: 3.8
Classifier: Programming Language :: Python :: 3.9
Requires-Dist: importlib-metadata (>=1.0,<2.0) ; python_version < "3.8"
Requires-Dist: matplotlib
Requires-Dist: seaborn
